Workbook

Sheet FACTURA
A1: PROFORMA
B3: DNI | C3: 1715236467001 | E3: TELÉFONO | F3: =VLOOKUP($C$3,CLIENTES!$B$3:$E$6,4,FALSE) -> 2345678
B5: CLIENTE | C5: =VLOOKUP($C$3,CLIENTES!$B$3:$E$6,2,FALSE) -> Mariela | E5: FORMA DE PAGO
B7: DIRECCIÓN | C7: =VLOOKUP($C$3,CLIENTES!$B$3:$E$6,3,FALSE) -> Avenida Colón | E7: FECHA
B10: CÓDIGO | C10: DESCRIPCIÓN | D10: PRECIO | E10: CANTIDAD | F10: IMPORTE
B11: ABC003 | C11: =IFERROR(VLOOKUP(B11,PRODUCTOS!$B$5:$D$8,2,FALSE),"") -> Mouse | D11: =IFERROR(VLOOKUP(B11,PRODUCTOS!$B$5:$D$8,3,FALSE),"") -> 5 | E11: 9 | F11: =IF(B11="","",IF(E11="","Introduce una cantidad",D11*E11)) -> 45
B12: ABC004 | C12: =IFERROR(VLOOKUP(B12,PRODUCTOS!$B$5:$D$8,2,FALSE),"") -> Teclado | D12: =IFERROR(VLOOKUP(B12,PRODUCTOS!$B$5:$D$8,3,FALSE),"") -> 10 | E12: 9 | F12: =IF(B12="","",IF(E12="","Introduce una cantidad",D12*E12)) -> 90
B13: ABC005 | C13: =IFERROR(VLOOKUP(B13,PRODUCTOS!$B$5:$D$8,2,FALSE),"") -> Lápiz | D13: =IFERROR(VLOOKUP(B13,PRODUCTOS!$B$5:$D$8,3,FALSE),"") -> 1.5 | E13: 18 | F13: =IF(B13="","",IF(E13="","Introduce una cantidad",D13*E13)) -> 27
B14: ABC007 | C14: =IFERROR(VLOOKUP(B14,PRODUCTOS!$B$5:$D$8,2,FALSE),"") -> Tutorial | D14: =IFERROR(VLOOKUP(B14,PRODUCTOS!$B$5:$D$8,3,FALSE),"") -> 15 | E14: 2 | F14: =IF(B14="","",IF(E14="","Introduce una cantidad",D14*E14)) -> 30
B15: ABC007 | C15: =IFERROR(VLOOKUP(B15,PRODUCTOS!$B$5:$D$8,2,FALSE),"") -> Tutorial | D15: =IFERROR(VLOOKUP(B15,PRODUCTOS!$B$5:$D$8,3,FALSE),"") -> 15 | E15: 1 | F15: =IF(B15="","",IF(E15="","Introduce una cantidad",D15*E15)) -> 15
E16: SUBTOTAL | F16: =SUM(F11:F15) -> 207
E17: IVA | F17: =F16*0.21 -> 43.47
E18: TOTAL | F18: =F16+F17 -> 250.47

Sheet CLIENTES
B2: DNI | C2: NOMBRE | D2: DIRECCIÓN | E2: TELÉFONO
B3: 1715236467001 | C3: Mariela | D3: Avenida Colón | E3: 2345678
B4: 1309970695001 | C4: Natalia | D4: C/ 6 de Diciembre | E4: 1234567
B5: 1707180178001 | C5: Elena | D5: C/ 10 de Agosto | E5: 7654321
B6: 1802452944001 | C6: Paty | D6: C/ Almagro | E6: 3214587

Sheet PRODUCTOS
B4: CÓDIGO | C4: ARTÍCULO | D4: PRECIO
B5: ABC003 | C5: Mouse | D5: 5
B6: ABC004 | C6: Teclado | D6: 10
B7: ABC005 | C7: Lápiz | D7: 1.5
B8: ABC007 | C8: Tutorial | D8: 15
